{
  "attributes": "base_table=x_g_nci_snowcicdtestapp_request",
  "attributes_override": true,
  "base_table": "sf_state_flow",
  "calculation": null,
  "calculation_override": false,
  "default_value": "x_g_nci_snowcicdtestapp_request",
  "default_value_override": true,
  "dependent": null,
  "dependent_override": false,
  "display_override": false,
  "element": "table",
  "mandatory": false,
  "mandatory_override": false,
  "name": "x_g_nci_snowcicdte_sfstapp_request",
  "read_only": false,
  "read_only_override": false,
  "reference_qual": null,
  "reference_qual_override": false,
  "sys_class_name": "sys_dictionary_override",
  "sys_created_by": "rizknt@nih.gov",
  "sys_created_on": "2020-04-14 16:08:53",
  "sys_id": "fee4a2671b44541094edddb6bc4bcb2c",
  "sys_mod_count": 0,
  "sys_name": "table",
  "sys_package": "e1e42e271b44541094edddb6bc4bcbde",
  "sys_policy": null,
  "sys_scope": "e1e42e271b44541094edddb6bc4bcbde",
  "sys_update_name": "sys_dictionary_override_fee4a2671b44541094edddb6bc4bcb2c",
  "sys_updated_by": "rizknt@nih.gov",
  "sys_updated_on": "2020-04-14 16:08:53"
}
