{
  "choices": null,
  "description": "Skills Weight",
  "ignore_cache": false,
  "is_private": false,
  "name": "x_g_nci_snowcicdte.skills.weight",
  "read_roles": "x_g_nci_snowcicdte_admin",
  "suffix": "skills.weight",
  "sys_class_name": "sys_properties",
  "sys_created_by": "rizknt@nih.gov",
  "sys_created_on": "2020-04-14 16:09:23",
  "sys_id": "02052a671b44541094edddb6bc4bcbd2",
  "sys_mod_count": 0,
  "sys_name": "x_g_nci_snowcicdte.skills.weight",
  "sys_package": "e1e42e271b44541094edddb6bc4bcbde",
  "sys_policy": null,
  "sys_scope": "e1e42e271b44541094edddb6bc4bcbde",
  "sys_update_name": "sys_properties_02052a671b44541094edddb6bc4bcbd2",
  "sys_updated_by": "rizknt@nih.gov",
  "sys_updated_on": "2020-04-14 16:09:23",
  "type": "integer",
  "value": 10,
  "write_roles": "x_g_nci_snowcicdte_admin"
}
