{
  "active": true,
  "automatic_condition": null,
  "automatic_roles": null,
  "automatic_script": "// when cancelling a task, clean up part sourcing data and clear all dependencies\nvar taskManager = new global.SMTask();\ntaskManager.cancelTransfers(current);\ntaskManager.clearDependencies(current);",
  "automatic_string": "current.state.changes()",
  "business_rule": "00f4e2671b44541094edddb6bc4bcba7",
  "change_client_script": null,
  "client_script": null,
  "comment": "SnowCICDTestApp Request State flow",
  "derived_from": "e5feb353df312100dca6a5f59bf263e4",
  "end_text": null,
  "ending_state": null,
  "event": null,
  "event_rule": null,
  "mandatory_fields": null,
  "manual_condition": null,
  "manual_roles": null,
  "manual_script": null,
  "manual_string": null,
  "name": "Cancel Cleanup",
  "not_mandatory": null,
  "not_read_only": null,
  "not_visible": null,
  "number": "SF0010026",
  "override": null,
  "read_only_fields": null,
  "roles": null,
  "start_text": 7,
  "starting_state": "1ae462671b44541094edddb6bc4bcb55",
  "sys_class_name": "x_g_nci_snowcicdte_sfstapp_task",
  "sys_created_by": "rizknt@nih.gov",
  "sys_created_on": "2020-04-14 16:08:58",
  "sys_id": "88f4e2671b44541094edddb6bc4bcb8d",
  "sys_mod_count": 0,
  "sys_name": "Cancel Cleanup",
  "sys_package": "e1e42e271b44541094edddb6bc4bcbde",
  "sys_policy": null,
  "sys_scope": "e1e42e271b44541094edddb6bc4bcbde",
  "sys_update_name": "x_g_nci_snowcicdte_sfstapp_task_88f4e2671b44541094edddb6bc4bcb8d",
  "sys_updated_by": "rizknt@nih.gov",
  "sys_updated_on": "2020-04-14 16:08:58",
  "table": "x_g_nci_snowcicdtestapp_task",
  "translated_ending_state": null,
  "translated_starting_state": "Cancelled",
  "ui_action": null,
  "visible_fields": null,
  "work_notes": null,
  "work_notes_rule": null
}
