{
  "dependent_value": null,
  "element": "state",
  "hint": "Task is assigned, acknowledged and pending work to start",
  "inactive": false,
  "label": "Accepted",
  "language": "en",
  "name": "x_g_nci_snowcicdtestapp_task",
  "sequence": 3,
  "sys_created_by": "rizknt@nih.gov",
  "sys_created_on": "2020-04-14 16:08:51",
  "sys_id": "5ae462671b44541094edddb6bc4bcb33",
  "sys_mod_count": 0,
  "sys_updated_by": "rizknt@nih.gov",
  "sys_updated_on": "2020-04-14 16:08:51",
  "u_dependent_value_2": null,
  "value": 17
}
